assertio/__init__.py
assertio/runner.py
assertio/bootstrap/__init__.py
assertio/bootstrap/bootstrap.py
assertio/bootstrap/config.py
assertio/decorators/__init__.py
assertio/decorators/decorators.py
assertio/requests/__init__.py
assertio/requests/action_request.py
assertio/requests/base_request.py
assertio/requests/precondition_request.py
assertio/requests/assertions/__init__.py
assertio/requests/assertions/body_assertions.py
assertio/requests/assertions/headers_assertions.py
assertio/requests/assertions/status_assertions.py
assertio/types/__init__.py
assertio-1.5.11.dist-info/LICENSE
assertio-1.5.11.dist-info/METADATA
assertio-1.5.11.dist-info/WHEEL
assertio-1.5.11.dist-info/entry_points.txt
assertio-1.5.11.dist-info/top_level.txt
assertio-1.5.11.dist-info/RECORD
