Metadata-Version: 2.1
Name: assertio
Version: 1.5.11
Summary: A pseudo-functional API Testing library.
Home-page: https://github.com/aldorvv/assertio
Author: Aldo Vázquez
Author-email: aldorvv@icloud.com
Project-URL: Bug Tracker, https://github.com/aldorvv/assertio/issues
Project-URL: Docs, https://assertio.readthedocs.io/en/latest/
Classifier: Programming Language :: Python :: 3
Classifier: License :: OSI Approved :: MIT License
Classifier: Operating System :: OS Independent
Requires-Python: >=3.8
License-File: LICENSE
Requires-Dist: loguru
Requires-Dist: pydash
Requires-Dist: pytruth
Requires-Dist: pyyaml
Requires-Dist: requests
